pyls_spyder/__init__.py
pyls_spyder/plugin.py
pyls_spyder/utils.py
pyls_spyder/tests/__init__.py
pyls_spyder/tests/test_plugin.py
pyls_spyder-0.3.1.dist-info/LICENSE
pyls_spyder-0.3.1.dist-info/METADATA
pyls_spyder-0.3.1.dist-info/WHEEL
pyls_spyder-0.3.1.dist-info/entry_points.txt
pyls_spyder-0.3.1.dist-info/top_level.txt
pyls_spyder-0.3.1.dist-info/RECORD
